{
  "baseline_t020": {
    "gate_threshold": "BASELINE_t0.20",
    "TP": 11069,
    "FP": 31056,
    "FN": 4096,
    "TN": 40486,
    "token_precision": 0.2628,
    "token_recall": 0.7299,
    "token_f1": 0.3864,
    "char_precision": 0.4751,
    "char_recall": 0.3223,
    "char_f1": 0.3841,
    "ans_precision": 0.4055,
    "ans_recall": 0.8196,
    "ans_f1": 0.5426,
    "gold_positive_rate": 0.1749,
    "predicted_positive_rate": 0.4858,
    "cat_A": 309,
    "cat_B": 68,
    "cat_C": 453,
    "cat_D": 426
  },
  "raw_best_char_f1": {
    "gate_threshold": "RAW",
    "TP": 14104,
    "FP": 48371,
    "FN": 1061,
    "TN": 23171,
    "token_precision": 0.2258,
    "token_recall": 0.93,
    "token_f1": 0.3633,
    "char_precision": 0.4297,
    "char_recall": 0.4324,
    "char_f1": 0.431,
    "ans_precision": 0.3633,
    "ans_recall": 0.9655,
    "ans_f1": 0.5279,
    "gold_positive_rate": 0.1749,
    "predicted_positive_rate": 0.7205,
    "cat_A": 364,
    "cat_B": 13,
    "cat_C": 638,
    "cat_D": 241,
    "token_threshold": 0.05,
    "gate_model": "NONE"
  },
  "raw_best_ans_f1": {
    "gate_threshold": "RAW",
    "TP": 12649,
    "FP": 38263,
    "FN": 2516,
    "TN": 33279,
    "token_precision": 0.2484,
    "token_recall": 0.8341,
    "token_f1": 0.3829,
    "char_precision": 0.4578,
    "char_recall": 0.3754,
    "char_f1": 0.4126,
    "ans_precision": 0.3979,
    "ans_recall": 0.8992,
    "ans_f1": 0.5517,
    "gold_positive_rate": 0.1749,
    "predicted_positive_rate": 0.5872,
    "cat_A": 339,
    "cat_B": 38,
    "cat_C": 513,
    "cat_D": 366,
    "token_threshold": 0.12,
    "gate_model": "NONE"
  },
  "lr_gate_best": {
    "gate_threshold": 0.25,
    "TP": 14015,
    "FP": 47076,
    "FN": 1150,
    "TN": 24466,
    "token_precision": 0.2294,
    "token_recall": 0.9242,
    "token_f1": 0.3676,
    "char_precision": 0.4376,
    "char_recall": 0.4306,
    "char_f1": 0.4341,
    "ans_precision": 0.3865,
    "ans_recall": 0.939,
    "ans_f1": 0.5476,
    "gold_positive_rate": 0.1749,
    "predicted_positive_rate": 0.7046,
    "cat_A": 354,
    "cat_B": 23,
    "cat_C": 562,
    "cat_D": 317,
    "token_threshold": 0.05,
    "gate_model": "LR"
  },
  "hg_gate_best": {
    "gate_threshold": 0.1,
    "TP": 14092,
    "FP": 48019,
    "FN": 1073,
    "TN": 23523,
    "token_precision": 0.2269,
    "token_recall": 0.9292,
    "token_f1": 0.3647,
    "char_precision": 0.4318,
    "char_recall": 0.4319,
    "char_f1": 0.4318,
    "ans_precision": 0.3713,
    "ans_recall": 0.9602,
    "ans_f1": 0.5355,
    "gold_positive_rate": 0.1749,
    "predicted_positive_rate": 0.7163,
    "cat_A": 362,
    "cat_B": 15,
    "cat_C": 613,
    "cat_D": 266,
    "token_threshold": 0.05,
    "gate_model": "HG"
  },
  "comparison": {
    "baseline_char_f1": 0.3841,
    "raw_best_char_f1": 0.431,
    "lr_gate_best_char_f1": 0.4341,
    "hg_gate_best_char_f1": 0.4318,
    "baseline_ans_f1": 0.5426,
    "raw_best_ans_f1": 0.5517,
    "lr_gate_best_ans_f1": 0.5476,
    "hg_gate_best_ans_f1": 0.5355
  },
  "reachability_summary": {
    "A": {
      "n": 309,
      "mean_visible_token_ratio": 1.0,
      "mean_visible_char_ratio": 0.9987443251617507,
      "mean_gold_char_recall": 0.9996983160550709,
      "mean_fully_vis_span_rate": 0.9995954692556634,
      "mean_partially_vis_rate": 0.0004045307443365696,
      "mean_fully_trunc_rate": 0.0
    },
    "B": {
      "n": 68,
      "mean_visible_token_ratio": 1.0,
      "mean_visible_char_ratio": 1.0,
      "mean_gold_char_recall": 1.0,
      "mean_fully_vis_span_rate": 1.0,
      "mean_partially_vis_rate": 0.0,
      "mean_fully_trunc_rate": 0.0
    },
    "C": {
      "n": 453,
      "mean_visible_token_ratio": 1.0,
      "mean_visible_char_ratio": 1.0,
      "mean_gold_char_recall": 0.0,
      "mean_fully_vis_span_rate": 0.0,
      "mean_partially_vis_rate": 0.0,
      "mean_fully_trunc_rate": 0.0
    },
    "D": {
      "n": 426,
      "mean_visible_token_ratio": 1.0,
      "mean_visible_char_ratio": 1.0,
      "mean_gold_char_recall": 0.0,
      "mean_fully_vis_span_rate": 0.0,
      "mean_partially_vis_rate": 0.0,
      "mean_fully_trunc_rate": 0.0
    }
  },
  "feature_columns": [
    "prob_max",
    "prob_mean",
    "prob_p90",
    "prob_p95",
    "prob_p99",
    "prob_top1_mean",
    "prob_top3_mean",
    "prob_top5_mean",
    "prob_sum",
    "prob_sum_norm",
    "count_above_005",
    "count_above_015",
    "ratio_above_005",
    "ratio_above_015",
    "n_pred_spans",
    "max_consecutive_high",
    "context_len",
    "question_len",
    "truncation_ratio",
    "prob_std",
    "prob_min"
  ],
  "n_train": 5012,
  "n_dev": 1256,
  "train_gate_accuracy_lr": 0.7289,
  "dev_gate_accuracy_lr": 0.7205,
  "train_gate_accuracy_hg": 0.8939,
  "dev_gate_accuracy_hg": 0.7094
}